django_ptvsd/__init__.py
django_ptvsd/management/__init__.py
django_ptvsd/management/commands/__init__.py
django_ptvsd/management/commands/runserver.py
django_ptvsd_debug-1.0.3.dist-info/LICENCE
django_ptvsd_debug-1.0.3.dist-info/METADATA
django_ptvsd_debug-1.0.3.dist-info/WHEEL
django_ptvsd_debug-1.0.3.dist-info/top_level.txt
django_ptvsd_debug-1.0.3.dist-info/RECORD
