Metadata-Version: 2.1
Name: django-ptvsd-debug
Version: 1.0.3
Summary: Multithreaded django hook for PTVSD debugging
Home-page: https://github.com/scottbarkman/django-ptvsd-debug
Author: Scott Barkman
Author-email: scottbarkman@gmail.com
License: UNKNOWN
Platform: UNKNOWN
Classifier: Programming Language :: Python :: 3
Classifier: License :: OSI Approved :: MIT License
Classifier: Operating System :: OS Independent
Requires-Dist: ptvsd (==4.*)
